oh_sanitizer/__init__.py
oh_sanitizer/field.ebnf
oh_sanitizer/main.py
oh_sanitizer-0.1.10.dist-info/LICENCE
oh_sanitizer-0.1.10.dist-info/METADATA
oh_sanitizer-0.1.10.dist-info/WHEEL
oh_sanitizer-0.1.10.dist-info/top_level.txt
oh_sanitizer-0.1.10.dist-info/RECORD
