Metadata-Version: 2.1
Name: oh-sanitizer
Version: 0.1.10
Summary: A corrector for the 'opening_hours' fields from OpenStreetMap.
Home-page: http://github.com/rezemika/oh_sanitizer
Author: rezemika
Author-email: reze.mika@gmail.com
License: UNKNOWN
Keywords: openstreetmap opening_hours
Platform: UNKNOWN
Classifier: Programming Language :: Python
Classifier: Development Status :: 3 - Alpha
Classifier: Intended Audience :: Developers
Classifier: License :: OSI Approved :: GNU Affero General Public License v3
Classifier: Operating System :: OS Independent
Classifier: Programming Language :: Python :: 2
Classifier: Programming Language :: Python :: 3
Classifier: Topic :: Utilities
Classifier: Topic :: Other/Nonlisted Topic
Requires-Dist: lark-parser
